.gitignore
.travis.yml
README.rst
gnarl.py
requirements.txt
setup.py
test.py
doc/Makefile
doc/apiref.rst
doc/conf.py
doc/index.rst
doc/knot.png
doc/make.bat
doc/quickstart.rst
gnarl.egg-info/PKG-INFO
gnarl.egg-info/SOURCES.txt
gnarl.egg-info/dependency_links.txt
gnarl.egg-info/requires.txt
gnarl.egg-info/top_level.txt