Metadata-Version: 1.1
Name: gnarl
Version: 0.1.0a4
Summary: Lightweight module to define serializable, schema-validated classes
Home-page: https://github.com/aperezdc/gnarl
Author: Adrián Pérez de Castro
Author-email: adrian@perezdecastro.org
License: MIT
Platform: UNKNOWN
Classifier: Development Status :: 3 - Alpha
Classifier: Intended Audience :: Developers
Classifier: Natural Language :: English
Classifier: Programming Language :: Python :: 3.4
Classifier: Programming Language :: Python
Classifier: Operating System :: OS Independent
